{"units": 2020, "features": 11582, "input shape": [null, 11582], "output shape": [null, 2020], "output dtype": "float32", "compute dtype": "float32", "workload": "dense", "layers": {"param": {"time": 0.0}, "tvmgen_default_fused_nn_contrib_dense_pack": {"time": 1.6059100000000002, "power": 89, "CPU0": 80, "DDR_AB": 5, "DDR_CD": 5, "CPU1": 24, "DDR_EF": 2, "DDR_GH": 0, "BLADE": 208}}, "batch_size": 1, "time": 1.6059100000000002, "power": 84.0, "memory": -1, "relay": "free_var %data: Tensor[(1, 11582), float32];\nnn.dense(%data, meta[relay.Constant][0], units=2020, out_dtype=\"float32\")\n"}