{"units": 4911, "features": 2792, "input shape": [null, 2792], "output shape": [null, 4911], "output dtype": "float32", "compute dtype": "float32", "workload": "dense", "layers": {"param": {"time": 0.0}, "tvmgen_default_fused_nn_contrib_dense_pack": {"time": 63.8711, "power": 31, "CPU0": 29, "DDR_AB": 1, "DDR_CD": 1, "CPU1": 16, "DDR_EF": 2, "DDR_GH": 0, "BLADE": 153}}, "batch_size": 64, "time": 63.8711, "power": 24.0, "memory": -1, "relay": "free_var %data: Tensor[(64, 2792), float32];\nnn.dense(%data, meta[relay.Constant][0], units=4911, out_dtype=\"float32\")\n"}