{"units": 3933, "features": 6618, "input shape": [null, 6618], "output shape": [null, 3933], "output dtype": "float32", "compute dtype": "float32", "workload": "dense", "layers": {"param": {"time": 0.0}, "tvmgen_default_fused_nn_contrib_dense_pack": {"time": 11.074300000000001, "power": 101, "CPU0": 95, "DDR_AB": 3, "DDR_CD": 3, "CPU1": 24, "DDR_EF": 1, "DDR_GH": 0, "BLADE": 202}}, "batch_size": 8, "time": 11.074300000000001, "power": 101.0, "memory": -1, "relay": "free_var %data: Tensor[(8, 6618), float32];\nnn.dense(%data, meta[relay.Constant][0], units=3933, out_dtype=\"float32\")\n"}