{"pool_size": [6, 6], "stride": [4, 4], "padding": "same", "input shape": [null, 160, 79, 3091], "output shape": [null, 19, 39, 3091], "output dtype": "float32", "compute dtype": "float32", "workload": "avg_pool2d", "strides": [4, 4], "layers": {"param": {"time": 0.0}, "tvmgen_default_fused_nn_avg_pool2d": {"time": 37.0385, "nvml:::Tesla_K80:device_0:power": 135108, "nvml:::Tesla_K80:device_0:gpu_utilization": 100, "nvml:::Tesla_K80:device_0:memory_utilization": 99, "nvml:::Tesla_K80:device_0:graphics_clock": 875, "nvml:::Tesla_K80:device_0:sm_clock": 875, "nvml:::Tesla_K80:device_0:memory_clock": 2505, "nvml:::Tesla_K80:device_0:allocated_memory": 5364776960}}, "data layout": "NCHW", "batch_size": 32, "time": 37.0385, "power": 132.357, "memory": 4.996337890625, "relay": "free_var %data: Tensor[(32, 3091, 79, 160), float32];\nnn.avg_pool2d(%data, pool_size=[6, 6], strides=[4, 4], padding=[0, 0, 0, 0], out_layout=\"NCHW\")"}