{"units": 4889, "features": 4893, "input shape": [null, 4893], "output shape": [null, 4889], "output dtype": "float32", "compute dtype": "float32", "workload": "dense", "layers": {"param": {"time": 0.0}, "tvmgen_default_fused_nn_contrib_dense_pack": {"time": 17647.551, "energy": 1035092, "powercap:::ENERGY_UJ:ZONE0": 1035092, "powercap:::ENERGY_UJ:ZONE0_SUBZONE0": 0, "powercap:::ENERGY_UJ:ZONE0_SUBZONE1": 0, "power": 58.653577485057276}}, "batch_size": 16, "time": 17.7315, "power": 61.756371468313134, "memory": -1, "relay": "free_var %data: Tensor[(16, 4893), float32];\nnn.dense(%data, meta[relay.Constant][0], units=4889, out_dtype=\"float32\")\n"}