{"units": 1795, "features": 3013, "input shape": [null, 3013], "output shape": [null, 1795], "output dtype": "float32", "compute dtype": "float32", "workload": "dense", "layers": {"param": {"time": 0.0}, "tvmgen_default_fused_nn_contrib_dense_pack": {"time": 10029.812, "energy": 467284, "powercap:::ENERGY_UJ:ZONE0": 467284, "powercap:::ENERGY_UJ:ZONE0_SUBZONE0": 0, "powercap:::ENERGY_UJ:ZONE0_SUBZONE1": 0, "power": 46.58950736065641}}, "batch_size": 1, "time": 0.6768, "power": 46.78743503906844, "memory": -1, "relay": "free_var %data: Tensor[(1, 3013), float32];\nnn.dense(%data, meta[relay.Constant][0], units=1795, out_dtype=\"float32\")\n"}