{"units": 2883, "features": 416, "input shape": [null, 416], "output shape": [null, 2883], "output dtype": "float32", "compute dtype": "float32", "workload": "dense", "layers": {"param": {"time": 0.0}, "tvmgen_default_fused_nn_contrib_dense_pack": {"time": 6572.385, "energy": 319335, "powercap:::ENERGY_UJ:ZONE0": 319335, "powercap:::ENERGY_UJ:ZONE0_SUBZONE0": 0, "powercap:::ENERGY_UJ:ZONE0_SUBZONE1": 0, "power": 48.58738494473467}}, "batch_size": 128, "time": 7.83758, "power": 58.7525291046142, "memory": -1, "relay": "free_var %data: Tensor[(128, 416), float32];\nnn.dense(%data, meta[relay.Constant][0], units=2883, out_dtype=\"float32\")\n"}