{"units": 1869, "features": 9061, "input shape": [null, 9061], "output shape": [null, 1869], "output dtype": "float32", "compute dtype": "float32", "workload": "dense", "layers": {"param": {"time": 0.0}, "tvmgen_default_fused_nn_contrib_dense_pack": {"time": 40.7542, "power": 89, "CPU0": 89, "DDR_AB": 0, "DDR_CD": 0, "CPU1": 21, "DDR_EF": 0, "DDR_GH": 0, "BLADE": 203}}, "batch_size": 512, "time": 40.7542, "power": 88.0, "memory": -1, "relay": "free_var %data: Tensor[(512, 9061), float32];\nnn.dense(%data, meta[relay.Constant][0], units=1869, out_dtype=\"float32\")\n"}