{"filters": 40, "kernel": [1, 1], "strides": [1, 1], "padding": "same", "dilation": [1, 1], "groups": 1, "input shape": [null, 132, 132, 240], "output shape": [null, 132, 132, 40], "output dtype": "float32", "compute dtype": "float32", "workload": "conv2d", "layers": {"param": {"time": 0.0}, "tvmgen_default_fused_layout_transform": {"time": 9.73332, "power": 59, "CPU0": 52, "DDR_AB": 3, "DDR_CD": 4, "CPU1": 20, "DDR_EF": 0, "DDR_GH": 0, "BLADE": 173}, "tvmgen_default_fused_nn_contrib_conv2d_NCHWc": {"time": 33.9778, "power": 93, "CPU0": 86, "DDR_AB": 3, "DDR_CD": 4, "CPU1": 26, "DDR_EF": 0, "DDR_GH": 0, "BLADE": 204}, "tvmgen_default_fused_layout_transform_1": {"time": 2.42267, "power": 21, "CPU0": 20, "DDR_AB": 0, "DDR_CD": 1, "CPU1": 17, "DDR_EF": 0, "DDR_GH": 0, "BLADE": 150}}, "data layout": "NCHW", "kernel layout": "OIHW", "batch_size": 16, "time": 33.9778, "power": 90.0, "memory": -1, "relay": "free_var %data: Tensor[(16, 240, 132, 132), float32];\nnn.conv2d(%data, meta[relay.Constant][0], padding=[0, 0, 0, 0], channels=40, kernel_size=[1, 1])\n"}