{"units": 613, "features": 3071, "input shape": [null, 3071], "output shape": [null, 613], "output dtype": "float32", "compute dtype": "float32", "workload": "dense", "layers": {"param": {"time": 0.0}, "tvmgen_default_fused_nn_dense": {"time": 0.34530500000000003, "nvml:::NVIDIA_A100-SXM4-40GB:device_0:power": 349409, "nvml:::NVIDIA_A100-SXM4-40GB:device_0:gpu_utilization": 94, "nvml:::NVIDIA_A100-SXM4-40GB:device_0:memory_utilization": 0, "nvml:::NVIDIA_A100-SXM4-40GB:device_0:graphics_clock": 1410, "nvml:::NVIDIA_A100-SXM4-40GB:device_0:sm_clock": 1410, "nvml:::NVIDIA_A100-SXM4-40GB:device_0:memory_clock": 1215, "nvml:::NVIDIA_A100-SXM4-40GB:device_0:allocated_memory": 446693376}}, "batch_size": 128, "time": 0.34530500000000003, "power": 343.434, "memory": 0.416015625, "relay": "free_var %data: Tensor[(128, 3071), float32];\nnn.dense(%data, meta[relay.Constant][0], units=613, out_dtype=\"float32\")\n"}