{"filters": 704, "kernel": [1, 1], "strides": [1, 1], "padding": "valid", "dilation": [1, 1], "groups": 704, "input shape": [null, 14, 14, 704], "output shape": [null, 14, 14, 704], "output dtype": "float32", "compute dtype": "float32", "workload": "conv2d", "layers": {"param": {"time": 0.0}, "tvmgen_default_fused_layout_transform": {"time": 11435.693, "energy": 428221, "powercap:::ENERGY_UJ:ZONE0": 428221, "powercap:::ENERGY_UJ:ZONE0_SUBZONE0": 0, "powercap:::ENERGY_UJ:ZONE0_SUBZONE1": 0, "power": 37.44600349099963}, "tvmgen_default_fused_nn_contrib_depthwise_conv2d_NCHWc": {"time": 11539.076, "energy": 513366, "powercap:::ENERGY_UJ:ZONE0": 513366, "powercap:::ENERGY_UJ:ZONE0_SUBZONE0": 0, "powercap:::ENERGY_UJ:ZONE0_SUBZONE1": 0, "power": 44.4893507937724}, "tvmgen_default_fused_layout_transform_1": {"time": 11858.676, "energy": 491636, "powercap:::ENERGY_UJ:ZONE0": 491636, "powercap:::ENERGY_UJ:ZONE0_SUBZONE0": 0, "powercap:::ENERGY_UJ:ZONE0_SUBZONE1": 0, "power": 41.45791654987454}}, "data layout": "NCHW", "batch_size": 32, "time": 1.98834, "power": 44.610733174954404, "memory": -1, "relay": "free_var %data: Tensor[(32, 704, 14, 14), float32];\nnn.conv2d(%data, meta[relay.Constant][0], padding=[0, 0, 0, 0], groups=704, channels=704, kernel_size=[1, 1])\n"}