{"filters": 32, "kernel": [1, 1], "strides": [1, 1], "padding": "same", "dilation": [1, 1], "groups": 32, "input shape": [null, 95, 95, 32], "output shape": [null, 95, 95, 32], "output dtype": "float32", "compute dtype": "float32", "workload": "conv2d", "layers": {"param": {"time": 0.0}, "tvmgen_default_fused_layout_transform": {"time": 17420.482, "energy": 692687, "powercap:::ENERGY_UJ:ZONE0": 692687, "powercap:::ENERGY_UJ:ZONE0_SUBZONE0": 0, "powercap:::ENERGY_UJ:ZONE0_SUBZONE1": 0, "power": 39.76279186764178}, "tvmgen_default_fused_nn_contrib_depthwise_conv2d_NCHWc": {"time": 17106.113, "energy": 724851, "powercap:::ENERGY_UJ:ZONE0": 724851, "powercap:::ENERGY_UJ:ZONE0_SUBZONE0": 0, "powercap:::ENERGY_UJ:ZONE0_SUBZONE1": 0, "power": 42.37379935465175}, "tvmgen_default_fused_layout_transform_1": {"time": 18526.83, "energy": 867003, "powercap:::ENERGY_UJ:ZONE0": 867003, "powercap:::ENERGY_UJ:ZONE0_SUBZONE0": 0, "powercap:::ENERGY_UJ:ZONE0_SUBZONE1": 0, "power": 46.79715849932233}}, "data layout": "NCHW", "batch_size": 64, "time": 8.76079, "power": 42.431452629152766, "memory": -1, "relay": "free_var %data: Tensor[(64, 32, 95, 95), float32];\nnn.conv2d(%data, meta[relay.Constant][0], padding=[0, 0, 0, 0], groups=32, channels=32, kernel_size=[1, 1])\n"}