{"filters": 24, "kernel": [1, 1], "strides": [1, 1], "padding": "same", "dilation": [1, 1], "groups": 24, "input shape": [null, 65, 65, 24], "output shape": [null, 65, 65, 24], "output dtype": "float32", "compute dtype": "float32", "workload": "conv2d", "layers": {"param": {"time": 0.0}, "tvmgen_default_fused_layout_transform": {"time": 8357.783, "energy": 334472, "powercap:::ENERGY_UJ:ZONE0": 334472, "powercap:::ENERGY_UJ:ZONE0_SUBZONE0": 0, "powercap:::ENERGY_UJ:ZONE0_SUBZONE1": 0, "power": 40.01922519404967}, "tvmgen_default_fused_nn_contrib_depthwise_conv2d_NCHWc": {"time": 9138.519, "energy": 387816, "powercap:::ENERGY_UJ:ZONE0": 387816, "powercap:::ENERGY_UJ:ZONE0_SUBZONE0": 0, "powercap:::ENERGY_UJ:ZONE0_SUBZONE1": 0, "power": 42.437510935852956}, "tvmgen_default_fused_layout_transform_1": {"time": 10572.327, "energy": 553466, "powercap:::ENERGY_UJ:ZONE0": 553466, "powercap:::ENERGY_UJ:ZONE0_SUBZONE0": 0, "powercap:::ENERGY_UJ:ZONE0_SUBZONE1": 0, "power": 52.350442811691316}}, "data layout": "NCHW", "batch_size": 16, "time": 0.544029, "power": 44.00781021929673, "memory": -1, "relay": "free_var %data: Tensor[(16, 24, 65, 65), float32];\nnn.conv2d(%data, meta[relay.Constant][0], padding=[0, 0, 0, 0], groups=24, channels=24, kernel_size=[1, 1])\n"}