{"filters": 112, "kernel": [1, 1], "strides": [1, 1], "padding": "same", "dilation": [1, 1], "groups": 112, "input shape": [null, 24, 24, 112], "output shape": [null, 24, 24, 112], "output dtype": "float32", "compute dtype": "float32", "workload": "conv2d", "layers": {"param": {"time": 0.0}, "tvmgen_default_fused_layout_transform": {"time": 11801.255, "energy": 458495, "powercap:::ENERGY_UJ:ZONE0": 458495, "powercap:::ENERGY_UJ:ZONE0_SUBZONE0": 0, "powercap:::ENERGY_UJ:ZONE0_SUBZONE1": 0, "power": 38.851376400221845}, "tvmgen_default_fused_nn_contrib_depthwise_conv2d_NCHWc": {"time": 11555.032, "energy": 462890, "powercap:::ENERGY_UJ:ZONE0": 462890, "powercap:::ENERGY_UJ:ZONE0_SUBZONE0": 0, "powercap:::ENERGY_UJ:ZONE0_SUBZONE1": 0, "power": 40.05960346972644}, "tvmgen_default_fused_layout_transform_1": {"time": 12307.914, "energy": 597654, "powercap:::ENERGY_UJ:ZONE0": 597654, "powercap:::ENERGY_UJ:ZONE0_SUBZONE0": 0, "powercap:::ENERGY_UJ:ZONE0_SUBZONE1": 0, "power": 48.55851283978747}}, "data layout": "NCHW", "batch_size": 128, "time": 3.88045, "power": 40.75668551137804, "memory": -1, "relay": "free_var %data: Tensor[(128, 112, 24, 24), float32];\nnn.conv2d(%data, meta[relay.Constant][0], padding=[0, 0, 0, 0], groups=112, channels=112, kernel_size=[1, 1])\n"}