{"filters": 18, "kernel": [1, 1], "strides": [1, 1], "padding": "same", "dilation": [1, 1], "groups": 18, "input shape": [null, 1, 1, 18], "output shape": [null, 1, 1, 18], "output dtype": "float32", "compute dtype": "float32", "workload": "conv2d", "layers": {"param": {"time": 0.0}, "tvmgen_default_fused_layout_transform": {"time": 8536.308, "energy": 363830, "powercap:::ENERGY_UJ:ZONE0": 363830, "powercap:::ENERGY_UJ:ZONE0_SUBZONE0": 0, "powercap:::ENERGY_UJ:ZONE0_SUBZONE1": 0, "power": 42.62147054675159}, "tvmgen_default_fused_nn_contrib_depthwise_conv2d_NCHWc": {"time": 9152.293, "energy": 355712, "powercap:::ENERGY_UJ:ZONE0": 355712, "powercap:::ENERGY_UJ:ZONE0_SUBZONE0": 0, "powercap:::ENERGY_UJ:ZONE0_SUBZONE1": 0, "power": 38.86588858114573}, "tvmgen_default_fused_layout_transform_1": {"time": 9178.377, "energy": 371032, "powercap:::ENERGY_UJ:ZONE0": 371032, "powercap:::ENERGY_UJ:ZONE0_SUBZONE0": 0, "powercap:::ENERGY_UJ:ZONE0_SUBZONE1": 0, "power": 40.424576153278515}}, "data layout": "NCHW", "batch_size": 1, "time": 0.00108405, "power": 38.581556862065476, "memory": -1, "relay": "free_var %data: Tensor[(1, 18, 1, 1), float32];\nnn.conv2d(%data, meta[relay.Constant][0], padding=[0, 0, 0, 0], groups=18, channels=18, kernel_size=[1, 1])\n"}