{"filters": 2048, "kernel": [1, 1], "strides": [1, 1], "padding": "same", "dilation": [1, 1], "groups": 2048, "input shape": [null, 8, 8, 2048], "output shape": [null, 8, 8, 2048], "output dtype": "float32", "compute dtype": "float32", "workload": "conv2d", "layers": {"param": {"time": 0.0}, "tvmgen_default_fused_layout_transform": {"time": 15517.912, "energy": 611449, "powercap:::ENERGY_UJ:ZONE0": 611449, "powercap:::ENERGY_UJ:ZONE0_SUBZONE0": 0, "powercap:::ENERGY_UJ:ZONE0_SUBZONE1": 0, "power": 39.40278821016642}, "tvmgen_default_fused_nn_contrib_depthwise_conv2d_NCHWc": {"time": 15654.179, "energy": 641844, "powercap:::ENERGY_UJ:ZONE0": 641844, "powercap:::ENERGY_UJ:ZONE0_SUBZONE0": 0, "powercap:::ENERGY_UJ:ZONE0_SUBZONE1": 0, "power": 41.001447600669444}, "tvmgen_default_fused_layout_transform_1": {"time": 15456.671, "energy": 680784, "powercap:::ENERGY_UJ:ZONE0": 680784, "powercap:::ENERGY_UJ:ZONE0_SUBZONE0": 0, "powercap:::ENERGY_UJ:ZONE0_SUBZONE1": 0, "power": 44.044671714886086}}, "data layout": "NCHW", "batch_size": 128, "time": 8.022440000000001, "power": 42.896755574424375, "memory": -1, "relay": "free_var %data: Tensor[(128, 2048, 8, 8), float32];\nnn.conv2d(%data, meta[relay.Constant][0], padding=[0, 0, 0, 0], groups=2048, channels=2048, kernel_size=[1, 1])\n"}