{"pool_size": [6, 6], "stride": [6, 6], "padding": "valid", "input shape": [null, 58, 184, 894], "output shape": [null, 30, 9, 894], "output dtype": "float32", "compute dtype": "float32", "workload": "max_pool2d", "strides": [6, 6], "layers": {"param": {"time": 0.0}, "tvmgen_default_fused_nn_max_pool2d": {"time": 4.73016, "nvml:::NVIDIA_GeForce_GTX_980_Ti:device_1:power": 148295, "nvml:::NVIDIA_GeForce_GTX_980_Ti:device_1:gpu_utilization": 100, "nvml:::NVIDIA_GeForce_GTX_980_Ti:device_1:memory_utilization": 100, "nvml:::NVIDIA_GeForce_GTX_980_Ti:device_1:graphics_clock": 1277, "nvml:::NVIDIA_GeForce_GTX_980_Ti:device_1:sm_clock": 1277, "nvml:::NVIDIA_GeForce_GTX_980_Ti:device_1:memory_clock": 3304, "nvml:::NVIDIA_GeForce_GTX_980_Ti:device_1:allocated_memory": 1356398592}}, "data layout": "NCHW", "batch_size": 32, "time": 4.73016, "power": 147.913, "memory": 1.26324462890625, "relay": "free_var %data: Tensor[(32, 894, 184, 58), float32];\nnn.max_pool2d(%data, pool_size=[6, 6], strides=[6, 6], padding=[0, 0, 0, 0], out_layout=\"NCHW\")"}