{"pool_size": [6, 6], "stride": [4, 4], "padding": "same", "input shape": [null, 161, 94, 2640], "output shape": [null, 23, 39, 2640], "output dtype": "float32", "compute dtype": "float32", "workload": "max_pool2d", "strides": [4, 4], "layers": {"param": {"time": 0.0}, "tvmgen_default_fused_nn_max_pool2d": {"time": 302173.012, "energy": 14655907, "powercap:::ENERGY_UJ:ZONE0": 14655907, "powercap:::ENERGY_UJ:ZONE0_SUBZONE0": 0, "powercap:::ENERGY_UJ:ZONE0_SUBZONE1": 0, "power": 48.5017073596235}}, "data layout": "NCHW", "batch_size": 1, "time": 9.20043, "power": 48.731943675642064, "memory": -1, "relay": "free_var %data: Tensor[(1, 2640, 94, 161), float32];\nnn.max_pool2d(%data, pool_size=[6, 6], strides=[4, 4], padding=[0, 0, 0, 0], out_layout=\"NCHW\")"}