{"pool_size": [6, 6], "stride": [6, 6], "padding": "valid", "input shape": [null, 176, 141, 3281], "output shape": [null, 23, 29, 3281], "output dtype": "float32", "compute dtype": "float32", "workload": "max_pool2d", "strides": [6, 6], "layers": {"param": {"time": 0.0}, "tvmgen_default_fused_nn_max_pool2d": {"time": 339881.801, "energy": 17068010, "powercap:::ENERGY_UJ:ZONE0": 17068010, "powercap:::ENERGY_UJ:ZONE0_SUBZONE0": 0, "powercap:::ENERGY_UJ:ZONE0_SUBZONE1": 0, "power": 50.217487225801776}}, "data layout": "NCHW", "batch_size": 1, "time": 10.3322, "power": 50.15962486947907, "memory": -1, "relay": "free_var %data: Tensor[(1, 3281, 141, 176), float32];\nnn.max_pool2d(%data, pool_size=[6, 6], strides=[6, 6], padding=[0, 0, 0, 0], out_layout=\"NCHW\")"}