{"pool_size": [6, 6], "stride": [6, 6], "padding": "same", "input shape": [null, 68, 13, 4076], "output shape": [null, 2, 11, 4076], "output dtype": "float32", "compute dtype": "float32", "workload": "avg_pool2d", "strides": [6, 6], "layers": {"param": {"time": 0.0}, "tvmgen_default_fused_nn_avg_pool2d": {"time": 26.724899999999998, "power": 92, "CPU0": 83, "DDR_AB": 5, "DDR_CD": 4, "CPU1": 26, "DDR_EF": 1, "DDR_GH": 0, "BLADE": 198}}, "data layout": "NCHW", "batch_size": 128, "time": 26.724899999999998, "power": 91.0, "memory": -1, "relay": "free_var %data: Tensor[(128, 4076, 13, 68), float32];\nnn.avg_pool2d(%data, pool_size=[6, 6], strides=[6, 6], padding=[0, 0, 0, 0], out_layout=\"NCHW\")"}