{"filters": 3840, "kernel": [1, 1], "strides": [1, 1], "padding": "same", "dilation": [1, 1], "groups": 3840, "input shape": [null, 1, 1, 3840], "output shape": [null, 1, 1, 3840], "output dtype": "float32", "compute dtype": "float32", "workload": "conv2d", "layers": {"param": {"time": 0.0}, "tvmgen_default_fused_layout_transform": {"time": 0.015860100000000002, "power": 25, "CPU0": 23, "DDR_AB": 1, "DDR_CD": 1, "CPU1": 16, "DDR_EF": 1, "DDR_GH": 0, "BLADE": 136}, "tvmgen_default_fused_nn_contrib_depthwise_conv2d_NCHWc": {"time": 0.31058, "power": 77, "CPU0": 74, "DDR_AB": 1, "DDR_CD": 2, "CPU1": 20, "DDR_EF": 1, "DDR_GH": 0, "BLADE": 173}, "tvmgen_default_fused_layout_transform_1": {"time": 0.0235669, "power": 39, "CPU0": 36, "DDR_AB": 1, "DDR_CD": 2, "CPU1": 29, "DDR_EF": 1, "DDR_GH": 0, "BLADE": 166}}, "data layout": "NCHW", "batch_size": 128, "time": 0.31058, "power": 75.0, "memory": -1, "relay": "free_var %data: Tensor[(128, 3840, 1, 1), float32];\nnn.conv2d(%data, meta[relay.Constant][0], padding=[0, 0, 0, 0], groups=3840, channels=3840, kernel_size=[1, 1])\n"}