{"filters": 128, "kernel": [1, 1], "strides": [1, 1], "padding": "valid", "dilation": [2, 2], "groups": 1, "input shape": [null, 7, 7, 1632], "output shape": [null, 7, 7, 128], "output dtype": "float32", "compute dtype": "float32", "workload": "conv2d", "layers": {"param": {"time": 0.0}, "tvmgen_default_fused_layout_transform": {"time": 620.546, "energy": 41687, "powercap:::ENERGY_UJ:ZONE0": 41687, "powercap:::ENERGY_UJ:ZONE0_SUBZONE0": 0, "powercap:::ENERGY_UJ:ZONE0_SUBZONE1": 0, "power": 67.17793684916187}, "tvmgen_default_fused_nn_contrib_conv2d_NCHWc": {"time": 9196.562, "energy": 530516, "powercap:::ENERGY_UJ:ZONE0": 530516, "powercap:::ENERGY_UJ:ZONE0_SUBZONE0": 0, "powercap:::ENERGY_UJ:ZONE0_SUBZONE1": 0, "power": 57.686339743047455}, "tvmgen_default_fused_layout_transform_1": {"time": 134.938, "energy": 0, "powercap:::ENERGY_UJ:ZONE0": 0, "powercap:::ENERGY_UJ:ZONE0_SUBZONE0": 0, "powercap:::ENERGY_UJ:ZONE0_SUBZONE1": 0, "power": 0.0}}, "data layout": "NCHW", "batch_size": 1, "time": 0.0981856, "power": 60.59315738289481, "memory": -1, "relay": "free_var %data: Tensor[(1, 1632, 7, 7), float32];\nnn.conv2d(%data, meta[relay.Constant][0], padding=[0, 0, 0, 0], dilation=[2, 2], channels=128, kernel_size=[1, 1])\n"}