{"filters": 128, "kernel": [1, 1], "strides": [1, 1], "padding": "valid", "dilation": [2, 2], "groups": 1, "input shape": [null, 7, 7, 1504], "output shape": [null, 7, 7, 128], "output dtype": "float32", "compute dtype": "float32", "workload": "conv2d", "layers": {"param": {"time": 0.0}, "tvmgen_default_fused_layout_transform": {"time": 2023.778, "energy": 87951, "powercap:::ENERGY_UJ:ZONE0": 87951, "powercap:::ENERGY_UJ:ZONE0_SUBZONE0": 0, "powercap:::ENERGY_UJ:ZONE0_SUBZONE1": 0, "power": 43.4588181114727}, "tvmgen_default_fused_nn_contrib_conv2d_NCHWc": {"time": 9251.588, "energy": 496825, "powercap:::ENERGY_UJ:ZONE0": 496825, "powercap:::ENERGY_UJ:ZONE0_SUBZONE0": 0, "powercap:::ENERGY_UJ:ZONE0_SUBZONE1": 0, "power": 53.70159155379596}, "tvmgen_default_fused_layout_transform_1": {"time": 77.44, "energy": 0, "powercap:::ENERGY_UJ:ZONE0": 0, "powercap:::ENERGY_UJ:ZONE0_SUBZONE0": 0, "powercap:::ENERGY_UJ:ZONE0_SUBZONE1": 0, "power": 0.0}}, "data layout": "NCHW", "batch_size": 32, "time": 5.32885, "power": 54.90308012559326, "memory": -1, "relay": "free_var %data: Tensor[(32, 1504, 7, 7), float32];\nnn.conv2d(%data, meta[relay.Constant][0], padding=[0, 0, 0, 0], dilation=[2, 2], channels=128, kernel_size=[1, 1])\n"}