{"filters": 96, "kernel": [3, 3], "strides": [1, 1], "padding": "same", "dilation": [2, 2], "groups": 1, "input shape": [null, 35, 35, 96], "output shape": [null, 31, 31, 96], "output dtype": "float32", "compute dtype": "float32", "workload": "conv2d", "layers": {"param": {"time": 0.0}, "tvmgen_default_fused_layout_transform": {"time": 1685.897, "energy": 44617, "powercap:::ENERGY_UJ:ZONE0": 44617, "powercap:::ENERGY_UJ:ZONE0_SUBZONE0": 0, "powercap:::ENERGY_UJ:ZONE0_SUBZONE1": 0, "power": 26.464843344522233}, "tvmgen_default_fused_nn_contrib_conv2d_NCHWc": {"time": 33500.155, "energy": 2114923, "powercap:::ENERGY_UJ:ZONE0": 2114923, "powercap:::ENERGY_UJ:ZONE0_SUBZONE0": 0, "powercap:::ENERGY_UJ:ZONE0_SUBZONE1": 0, "power": 63.13173774867609}, "tvmgen_default_fused_layout_transform_1": {"time": 1232.426, "energy": 56458, "powercap:::ENERGY_UJ:ZONE0": 56458, "powercap:::ENERGY_UJ:ZONE0_SUBZONE0": 0, "powercap:::ENERGY_UJ:ZONE0_SUBZONE1": 0, "power": 45.810458396690755}}, "data layout": "NCHW", "batch_size": 32, "time": 33.603899999999996, "power": 63.23643101371375, "memory": -1, "relay": "free_var %data: Tensor[(32, 96, 35, 35), float32];\nnn.conv2d(%data, meta[relay.Constant][0], padding=[0, 0, 0, 0], dilation=[2, 2], channels=96, kernel_size=[3, 3])\n"}