{"filters": 256, "kernel": [1, 1], "strides": [1, 1], "padding": "same", "dilation": [2, 2], "groups": 1, "input shape": [null, 28, 28, 128], "output shape": [null, 28, 28, 256], "output dtype": "float32", "compute dtype": "float32", "workload": "conv2d", "layers": {"param": {"time": 0.0}, "tvmgen_default_fused_layout_transform": {"time": 6029.716, "energy": 283691, "powercap:::ENERGY_UJ:ZONE0": 283691, "powercap:::ENERGY_UJ:ZONE0_SUBZONE0": 0, "powercap:::ENERGY_UJ:ZONE0_SUBZONE1": 0, "power": 47.04881622948742}, "tvmgen_default_fused_nn_contrib_conv2d_NCHWc": {"time": 47825.62, "energy": 2879998, "powercap:::ENERGY_UJ:ZONE0": 2879998, "powercap:::ENERGY_UJ:ZONE0_SUBZONE0": 0, "powercap:::ENERGY_UJ:ZONE0_SUBZONE1": 0, "power": 60.21872795376202}, "tvmgen_default_fused_layout_transform_1": {"time": 11741.172, "energy": 506286, "powercap:::ENERGY_UJ:ZONE0": 506286, "powercap:::ENERGY_UJ:ZONE0_SUBZONE0": 0, "powercap:::ENERGY_UJ:ZONE0_SUBZONE1": 0, "power": 43.12056752085737}}, "data layout": "NCHW", "batch_size": 128, "time": 48.118300000000005, "power": 60.755545729900206, "memory": -1, "relay": "free_var %data: Tensor[(128, 128, 28, 28), float32];\nnn.conv2d(%data, meta[relay.Constant][0], padding=[0, 0, 0, 0], dilation=[2, 2], channels=256, kernel_size=[1, 1])\n"}