{"filters": 64, "kernel": [1, 1], "strides": [1, 1], "padding": "valid", "dilation": [2, 2], "groups": 1, "input shape": [null, 56, 56, 256], "output shape": [null, 56, 56, 64], "output dtype": "float32", "compute dtype": "float32", "workload": "conv2d", "layers": {"param": {"time": 0.0}, "tvmgen_default_fused_layout_transform": {"time": 993.707, "energy": 63172, "powercap:::ENERGY_UJ:ZONE0": 63172, "powercap:::ENERGY_UJ:ZONE0_SUBZONE0": 0, "powercap:::ENERGY_UJ:ZONE0_SUBZONE1": 0, "power": 63.57205896707983}, "tvmgen_default_fused_nn_contrib_conv2d_NCHWc": {"time": 10004.314, "energy": 639891, "powercap:::ENERGY_UJ:ZONE0": 639891, "powercap:::ENERGY_UJ:ZONE0_SUBZONE0": 0, "powercap:::ENERGY_UJ:ZONE0_SUBZONE1": 0, "power": 63.961507005877664}, "tvmgen_default_fused_layout_transform_1": {"time": 645.798, "energy": 0, "powercap:::ENERGY_UJ:ZONE0": 0, "powercap:::ENERGY_UJ:ZONE0_SUBZONE0": 0, "powercap:::ENERGY_UJ:ZONE0_SUBZONE1": 0, "power": 0.0}}, "data layout": "NCHW", "batch_size": 1, "time": 0.6053299999999999, "power": 64.61788586808476, "memory": -1, "relay": "free_var %data: Tensor[(1, 256, 56, 56), float32];\nnn.conv2d(%data, meta[relay.Constant][0], padding=[0, 0, 0, 0], dilation=[2, 2], channels=64, kernel_size=[1, 1])\n"}