{"units": 3651, "features": 8439, "input shape": [null, 8439], "output shape": [null, 3651], "output dtype": "float32", "compute dtype": "float32", "workload": "dense", "layers": {"param": {"time": 0.0}, "tvmgen_default_fused_nn_dense": {"time": 55.1493, "nvml:::Tesla_K80:device_0:power": 150908, "nvml:::Tesla_K80:device_0:gpu_utilization": 100, "nvml:::Tesla_K80:device_0:memory_utilization": 100, "nvml:::Tesla_K80:device_0:graphics_clock": 849, "nvml:::Tesla_K80:device_0:sm_clock": 849, "nvml:::Tesla_K80:device_0:memory_clock": 2505, "nvml:::Tesla_K80:device_0:allocated_memory": 197132288}}, "batch_size": 64, "time": 55.1493, "power": 150.574, "memory": 0.18359375, "relay": "free_var %data: Tensor[(64, 8439), float32];\nnn.dense(%data, meta[relay.Constant][0], units=3651, out_dtype=\"float32\")\n"}