{"units": 2602, "features": 13588, "input shape": [null, 13588], "output shape": [null, 2602], "output dtype": "float32", "compute dtype": "float32", "workload": "dense", "layers": {"param": {"time": 0.0}, "tvmgen_default_fused_nn_dense": {"time": 2.36789, "nvml:::Tesla_K80:device_0:power": 84101, "nvml:::Tesla_K80:device_0:gpu_utilization": 100, "nvml:::Tesla_K80:device_0:memory_utilization": 32, "nvml:::Tesla_K80:device_0:graphics_clock": 562, "nvml:::Tesla_K80:device_0:sm_clock": 562, "nvml:::Tesla_K80:device_0:memory_clock": 2505, "nvml:::Tesla_K80:device_0:allocated_memory": 212992000}}, "batch_size": 1, "time": 2.36789, "power": 83.882, "memory": 0.1983642578125, "relay": "free_var %data: Tensor[(1, 13588), float32];\nnn.dense(%data, meta[relay.Constant][0], units=2602, out_dtype=\"float32\")\n"}