{"units": 3544, "features": 82, "input shape": [null, 82], "output shape": [null, 3544], "output dtype": "float32", "compute dtype": "float32", "workload": "dense", "layers": {"param": {"time": 0.0}, "tvmgen_default_fused_nn_dense": {"time": 0.0378313, "nvml:::Tesla_K80:device_0:power": 116874, "nvml:::Tesla_K80:device_0:gpu_utilization": 77, "nvml:::Tesla_K80:device_0:memory_utilization": 1, "nvml:::Tesla_K80:device_0:graphics_clock": 875, "nvml:::Tesla_K80:device_0:sm_clock": 875, "nvml:::Tesla_K80:device_0:memory_clock": 2505, "nvml:::Tesla_K80:device_0:allocated_memory": 72744960}}, "batch_size": 1, "time": 0.0378313, "power": 114.1705, "memory": 0.0677490234375, "relay": "free_var %data: Tensor[(1, 82), float32];\nnn.dense(%data, meta[relay.Constant][0], units=3544, out_dtype=\"float32\")\n"}