{"units": 2992, "features": 22992, "input shape": [null, 22992], "output shape": [null, 2992], "output dtype": "float32", "compute dtype": "float32", "workload": "dense", "layers": {"param": {"time": 0.0}, "tvmgen_default_fused_nn_dense": {"time": 59.5279, "nvml:::Tesla_K80:device_0:power": 151349, "nvml:::Tesla_K80:device_0:gpu_utilization": 100, "nvml:::Tesla_K80:device_0:memory_utilization": 100, "nvml:::Tesla_K80:device_0:graphics_clock": 862, "nvml:::Tesla_K80:device_0:sm_clock": 862, "nvml:::Tesla_K80:device_0:memory_clock": 2505, "nvml:::Tesla_K80:device_0:allocated_memory": 349831168}}, "batch_size": 32, "time": 59.5279, "power": 150.8245, "memory": 0.3258056640625, "relay": "free_var %data: Tensor[(32, 22992), float32];\nnn.dense(%data, meta[relay.Constant][0], units=2992, out_dtype=\"float32\")\n"}