{"units": 138, "features": 22013, "input shape": [null, 22013], "output shape": [null, 138], "output dtype": "float32", "compute dtype": "float32", "workload": "dense", "layers": {"param": {"time": 0.0}, "tvmgen_default_fused_nn_dense": {"time": 1.64168, "nvml:::Tesla_K80:device_0:power": 101767, "nvml:::Tesla_K80:device_0:gpu_utilization": 100, "nvml:::Tesla_K80:device_0:memory_utilization": 62, "nvml:::Tesla_K80:device_0:graphics_clock": 562, "nvml:::Tesla_K80:device_0:sm_clock": 562, "nvml:::Tesla_K80:device_0:memory_clock": 2505, "nvml:::Tesla_K80:device_0:allocated_memory": 85196800}}, "batch_size": 16, "time": 1.64168, "power": 99.513, "memory": 0.079345703125, "relay": "free_var %data: Tensor[(16, 22013), float32];\nnn.dense(%data, meta[relay.Constant][0], units=138, out_dtype=\"float32\")\n"}