{"units": 4391, "features": 20466, "input shape": [null, 20466], "output shape": [null, 4391], "output dtype": "float32", "compute dtype": "float32", "workload": "dense", "layers": {"param": {"time": 0.0}, "tvmgen_default_fused_nn_dense": {"time": 318.77, "nvml:::Tesla_K80:device_0:power": 150986, "nvml:::Tesla_K80:device_0:gpu_utilization": 100, "nvml:::Tesla_K80:device_0:memory_utilization": 100, "nvml:::Tesla_K80:device_0:graphics_clock": 849, "nvml:::Tesla_K80:device_0:sm_clock": 849, "nvml:::Tesla_K80:device_0:memory_clock": 2505, "nvml:::Tesla_K80:device_0:allocated_memory": 442892288}}, "batch_size": 128, "time": 318.77, "power": 149.087, "memory": 0.4124755859375, "relay": "free_var %data: Tensor[(128, 20466), float32];\nnn.dense(%data, meta[relay.Constant][0], units=4391, out_dtype=\"float32\")\n"}