{"units": 3227, "features": 24427, "input shape": [null, 24427], "output shape": [null, 3227], "output dtype": "float32", "compute dtype": "float32", "workload": "dense", "layers": {"param": {"time": 0.0}, "tvmgen_default_fused_nn_dense": {"time": 163.25799999999998, "nvml:::Tesla_K80:device_0:power": 146190, "nvml:::Tesla_K80:device_0:gpu_utilization": 100, "nvml:::Tesla_K80:device_0:memory_utilization": 94, "nvml:::Tesla_K80:device_0:graphics_clock": 875, "nvml:::Tesla_K80:device_0:sm_clock": 875, "nvml:::Tesla_K80:device_0:memory_clock": 2505, "nvml:::Tesla_K80:device_0:allocated_memory": 393216000}}, "batch_size": 64, "time": 163.25799999999998, "power": 146.023, "memory": 0.3662109375, "relay": "free_var %data: Tensor[(64, 24427), float32];\nnn.dense(%data, meta[relay.Constant][0], units=3227, out_dtype=\"float32\")\n"}