{"units": 4664, "features": 19639, "input shape": [null, 19639], "output shape": [null, 4664], "output dtype": "float32", "compute dtype": "float32", "workload": "dense", "layers": {"param": {"time": 0.0}, "tvmgen_default_fused_nn_dense": {"time": 6.02175, "nvml:::Tesla_K80:device_0:power": 84728, "nvml:::Tesla_K80:device_0:gpu_utilization": 100, "nvml:::Tesla_K80:device_0:memory_utilization": 33, "nvml:::Tesla_K80:device_0:graphics_clock": 562, "nvml:::Tesla_K80:device_0:sm_clock": 562, "nvml:::Tesla_K80:device_0:memory_clock": 2505, "nvml:::Tesla_K80:device_0:allocated_memory": 438042624}}, "batch_size": 1, "time": 6.02175, "power": 84.385, "memory": 0.407958984375, "relay": "free_var %data: Tensor[(1, 19639), float32];\nnn.dense(%data, meta[relay.Constant][0], units=4664, out_dtype=\"float32\")\n"}