{"units": 458, "features": 12189, "input shape": [null, 12189], "output shape": [null, 458], "output dtype": "float32", "compute dtype": "float32", "workload": "dense", "layers": {"param": {"time": 0.0}, "tvmgen_default_fused_nn_dense": {"time": 0.353137, "nvml:::Tesla_K80:device_0:power": 114649, "nvml:::Tesla_K80:device_0:gpu_utilization": 99, "nvml:::Tesla_K80:device_0:memory_utilization": 50, "nvml:::Tesla_K80:device_0:graphics_clock": 875, "nvml:::Tesla_K80:device_0:sm_clock": 875, "nvml:::Tesla_K80:device_0:memory_clock": 2505, "nvml:::Tesla_K80:device_0:allocated_memory": 95027200}}, "batch_size": 1, "time": 0.353137, "power": 112.778, "memory": 0.0885009765625, "relay": "free_var %data: Tensor[(1, 12189), float32];\nnn.dense(%data, meta[relay.Constant][0], units=458, out_dtype=\"float32\")\n"}