{"units": 2292, "features": 14267, "input shape": [null, 14267], "output shape": [null, 2292], "output dtype": "float32", "compute dtype": "float32", "workload": "dense", "layers": {"param": {"time": 0.0}, "tvmgen_default_fused_nn_dense": {"time": 97.8136, "nvml:::Tesla_K80:device_0:power": 133720, "nvml:::Tesla_K80:device_0:gpu_utilization": 100, "nvml:::Tesla_K80:device_0:memory_utilization": 66, "nvml:::Tesla_K80:device_0:graphics_clock": 875, "nvml:::Tesla_K80:device_0:sm_clock": 875, "nvml:::Tesla_K80:device_0:memory_clock": 2505, "nvml:::Tesla_K80:device_0:allocated_memory": 206045184}}, "batch_size": 64, "time": 97.8136, "power": 133.246, "memory": 0.19189453125, "relay": "free_var %data: Tensor[(64, 14267), float32];\nnn.dense(%data, meta[relay.Constant][0], units=2292, out_dtype=\"float32\")\n"}