{"units": 4024, "features": 8348, "input shape": [null, 8348], "output shape": [null, 4024], "output dtype": "float32", "compute dtype": "float32", "workload": "dense", "layers": {"param": {"time": 0.0}, "tvmgen_default_fused_nn_dense": {"time": 25.275100000000002, "nvml:::Tesla_K80:device_0:power": 141501, "nvml:::Tesla_K80:device_0:gpu_utilization": 100, "nvml:::Tesla_K80:device_0:memory_utilization": 67, "nvml:::Tesla_K80:device_0:graphics_clock": 875, "nvml:::Tesla_K80:device_0:sm_clock": 875, "nvml:::Tesla_K80:device_0:memory_clock": 2505, "nvml:::Tesla_K80:device_0:allocated_memory": 206045184}}, "batch_size": 16, "time": 25.275100000000002, "power": 140.675, "memory": 0.19189453125, "relay": "free_var %data: Tensor[(16, 8348), float32];\nnn.dense(%data, meta[relay.Constant][0], units=4024, out_dtype=\"float32\")\n"}