{"units": 2342, "features": 5615, "input shape": [null, 5615], "output shape": [null, 2342], "output dtype": "float32", "compute dtype": "float32", "workload": "dense", "layers": {"param": {"time": 0.0}, "tvmgen_default_fused_nn_dense": {"time": 23.3779, "nvml:::Tesla_K80:device_0:power": 159642, "nvml:::Tesla_K80:device_0:gpu_utilization": 100, "nvml:::Tesla_K80:device_0:memory_utilization": 100, "nvml:::Tesla_K80:device_0:graphics_clock": 849, "nvml:::Tesla_K80:device_0:sm_clock": 849, "nvml:::Tesla_K80:device_0:memory_clock": 2505, "nvml:::Tesla_K80:device_0:allocated_memory": 125698048}}, "batch_size": 64, "time": 23.3779, "power": 156.798, "memory": 0.1170654296875, "relay": "free_var %data: Tensor[(64, 5615), float32];\nnn.dense(%data, meta[relay.Constant][0], units=2342, out_dtype=\"float32\")\n"}