{"filters": 768, "kernel": [1, 1], "strides": [1, 1], "padding": "valid", "dilation": [1, 1], "groups": 768, "input shape": [null, 14, 14, 768], "output shape": [null, 14, 14, 768], "output dtype": "float32", "compute dtype": "float32", "workload": "conv2d", "layers": {"param": {"time": 0.0}, "tvmgen_default_fused_nn_conv2d": {"time": 9.70093, ":MEAS:SCAL:VOLT:DC? CH1": 5000, ":MEAS:SCAL:CURR:DC? CH1": 844, "power": 4.22}}, "data layout": "NCHW", "batch_size": 16, "time": 9.70093, "power": 4.297499999999999, "io_size": 9633792, "ws_size": 9633808, "relay": "free_var %data: Tensor[(16, 768, 14, 14), float32];\nnn.conv2d(%data, meta[relay.Constant][0], padding=[0, 0, 0, 0], groups=768, channels=768, kernel_size=[1, 1])\n"}