{"filters": 32, "kernel": [3, 3], "strides": [1, 1], "padding": "same", "dilation": [8, 8], "groups": 1, "input shape": [null, 35, 35, 32], "output shape": [null, 19, 19, 32], "output dtype": "float32", "compute dtype": "float32", "workload": "conv2d", "layers": {"param": {"time": 0.0}, "tvmgen_default_fused_layout_transform": {"time": 4.22036, "power": 69, "CPU0": 61, "DDR_AB": 4, "DDR_CD": 4, "CPU1": 19, "DDR_EF": 0, "DDR_GH": 1, "BLADE": 187}, "tvmgen_default_fused_nn_contrib_conv2d_NCHWc": {"time": 9.159820000000002, "power": 110, "CPU0": 106, "DDR_AB": 2, "DDR_CD": 2, "CPU1": 25, "DDR_EF": 0, "DDR_GH": 1, "BLADE": 223}, "tvmgen_default_fused_layout_transform_1": {"time": 1.03999, "power": 28, "CPU0": 26, "DDR_AB": 1, "DDR_CD": 1, "CPU1": 15, "DDR_EF": 0, "DDR_GH": 1, "BLADE": 162}}, "data layout": "NCHW", "batch_size": 512, "time": 9.159820000000002, "power": 99.0, "memory": -1, "relay": "free_var %data: Tensor[(512, 32, 35, 35), float32];\nnn.conv2d(%data, meta[relay.Constant][0], padding=[0, 0, 0, 0], dilation=[8, 8], channels=32, kernel_size=[3, 3])\n"}