{"filters": 144, "kernel": [1, 1], "strides": [1, 1], "padding": "same", "dilation": [4, 4], "groups": 1, "input shape": [null, 60, 60, 24], "output shape": [null, 60, 60, 144], "output dtype": "float32", "compute dtype": "float32", "workload": "conv2d", "layers": {"param": {"time": 0.0}, "tvmgen_default_fused_layout_transform": {"time": 0.5366019999999999, "power": 15, "CPU0": 15, "DDR_AB": 0, "DDR_CD": 0, "CPU1": 14, "DDR_EF": 0, "DDR_GH": 0, "BLADE": 117}, "tvmgen_default_fused_nn_contrib_conv2d_NCHWc": {"time": 4.275720000000001, "power": 96, "CPU0": 91, "DDR_AB": 3, "DDR_CD": 2, "CPU1": 23, "DDR_EF": 0, "DDR_GH": 0, "BLADE": 206}, "tvmgen_default_fused_layout_transform_1": {"time": 3.70526, "power": 92, "CPU0": 82, "DDR_AB": 5, "DDR_CD": 5, "CPU1": 22, "DDR_EF": 0, "DDR_GH": 0, "BLADE": 210}}, "data layout": "NCHW", "batch_size": 32, "time": 4.275720000000001, "power": 96.0, "memory": -1, "relay": "free_var %data: Tensor[(32, 24, 60, 60), float32];\nnn.conv2d(%data, meta[relay.Constant][0], padding=[0, 0, 0, 0], dilation=[4, 4], channels=144, kernel_size=[1, 1])\n"}