{"filters": 24, "kernel": [1, 1], "strides": [1, 1], "padding": "same", "dilation": [8, 8], "groups": 1, "input shape": [null, 65, 65, 144], "output shape": [null, 65, 65, 24], "output dtype": "float32", "compute dtype": "float32", "workload": "conv2d", "layers": {"param": {"time": 0.0}, "tvmgen_default_fused_layout_transform": {"time": 47.4163, "power": 94, "CPU0": 82, "DDR_AB": 5, "DDR_CD": 7, "CPU1": 27, "DDR_EF": 1, "DDR_GH": 0, "BLADE": 196}, "tvmgen_default_fused_nn_contrib_conv2d_NCHWc": {"time": 55.4097, "power": 117, "CPU0": 107, "DDR_AB": 5, "DDR_CD": 6, "CPU1": 26, "DDR_EF": 1, "DDR_GH": 0, "BLADE": 227}, "tvmgen_default_fused_layout_transform_1": {"time": 10.9149, "power": 55, "CPU0": 50, "DDR_AB": 2, "DDR_CD": 3, "CPU1": 19, "DDR_EF": 1, "DDR_GH": 0, "BLADE": 180}}, "data layout": "NCHW", "batch_size": 512, "time": 55.4097, "power": 115.0, "memory": -1, "relay": "free_var %data: Tensor[(512, 144, 65, 65), float32];\nnn.conv2d(%data, meta[relay.Constant][0], padding=[0, 0, 0, 0], dilation=[8, 8], channels=24, kernel_size=[1, 1])\n"}