{"units": 3685, "features": 15187, "input shape": [null, 15187], "output shape": [null, 3685], "output dtype": "float32", "compute dtype": "float32", "workload": "dense", "layers": {"param": {"time": 0.0}, "tvmgen_default_fused_nn_dense": {"time": 112.422, "nvml:::NVIDIA_GeForce_GTX_980_Ti:device_1:power": 190914, "nvml:::NVIDIA_GeForce_GTX_980_Ti:device_1:gpu_utilization": 100, "nvml:::NVIDIA_GeForce_GTX_980_Ti:device_1:memory_utilization": 100, "nvml:::NVIDIA_GeForce_GTX_980_Ti:device_1:graphics_clock": 1265, "nvml:::NVIDIA_GeForce_GTX_980_Ti:device_1:sm_clock": 1265, "nvml:::NVIDIA_GeForce_GTX_980_Ti:device_1:memory_clock": 3304, "nvml:::NVIDIA_GeForce_GTX_980_Ti:device_1:allocated_memory": 337313792}}, "batch_size": 128, "time": 112.422, "power": 190.521, "memory": 0.31414794921875, "relay": "free_var %data: Tensor[(128, 15187), float32];\nnn.dense(%data, meta[relay.Constant][0], units=3685, out_dtype=\"float32\")\n"}