{"units": 775, "features": 22789, "input shape": [null, 22789], "output shape": [null, 775], "output dtype": "float32", "compute dtype": "float32", "workload": "dense", "layers": {"param": {"time": 0.0}, "tvmgen_default_fused_nn_dense": {"time": 35.7092, "nvml:::NVIDIA_GeForce_GTX_980_Ti:device_1:power": 183440, "nvml:::NVIDIA_GeForce_GTX_980_Ti:device_1:gpu_utilization": 99, "nvml:::NVIDIA_GeForce_GTX_980_Ti:device_1:memory_utilization": 100, "nvml:::NVIDIA_GeForce_GTX_980_Ti:device_1:graphics_clock": 1265, "nvml:::NVIDIA_GeForce_GTX_980_Ti:device_1:sm_clock": 1265, "nvml:::NVIDIA_GeForce_GTX_980_Ti:device_1:memory_clock": 3304, "nvml:::NVIDIA_GeForce_GTX_980_Ti:device_1:allocated_memory": 187105280}}, "batch_size": 128, "time": 35.7092, "power": 183.065, "memory": 0.17425537109375, "relay": "free_var %data: Tensor[(128, 22789), float32];\nnn.dense(%data, meta[relay.Constant][0], units=775, out_dtype=\"float32\")\n"}