{"units": 1109, "features": 19032, "input shape": [null, 19032], "output shape": [null, 1109], "output dtype": "float32", "compute dtype": "float32", "workload": "dense", "layers": {"param": {"time": 0.0}, "tvmgen_default_fused_nn_dense": {"time": 21.5789, "nvml:::NVIDIA_GeForce_GTX_980_Ti:device_1:power": 184764, "nvml:::NVIDIA_GeForce_GTX_980_Ti:device_1:gpu_utilization": 100, "nvml:::NVIDIA_GeForce_GTX_980_Ti:device_1:memory_utilization": 100, "nvml:::NVIDIA_GeForce_GTX_980_Ti:device_1:graphics_clock": 1265, "nvml:::NVIDIA_GeForce_GTX_980_Ti:device_1:sm_clock": 1265, "nvml:::NVIDIA_GeForce_GTX_980_Ti:device_1:memory_clock": 3304, "nvml:::NVIDIA_GeForce_GTX_980_Ti:device_1:allocated_memory": 194183168}}, "batch_size": 64, "time": 21.5789, "power": 184.37, "memory": 0.18084716796875, "relay": "free_var %data: Tensor[(64, 19032), float32];\nnn.dense(%data, meta[relay.Constant][0], units=1109, out_dtype=\"float32\")\n"}