{"units": 1953, "features": 18569, "input shape": [null, 18569], "output shape": [null, 1953], "output dtype": "float32", "compute dtype": "float32", "workload": "dense", "layers": {"param": {"time": 0.0}, "tvmgen_default_fused_nn_dense": {"time": 36.4543, "nvml:::NVIDIA_GeForce_GTX_980_Ti:device_1:power": 183631, "nvml:::NVIDIA_GeForce_GTX_980_Ti:device_1:gpu_utilization": 99, "nvml:::NVIDIA_GeForce_GTX_980_Ti:device_1:memory_utilization": 100, "nvml:::NVIDIA_GeForce_GTX_980_Ti:device_1:graphics_clock": 1265, "nvml:::NVIDIA_GeForce_GTX_980_Ti:device_1:sm_clock": 1265, "nvml:::NVIDIA_GeForce_GTX_980_Ti:device_1:memory_clock": 3304, "nvml:::NVIDIA_GeForce_GTX_980_Ti:device_1:allocated_memory": 254607360}}, "batch_size": 64, "time": 36.4543, "power": 183.357, "memory": 0.23712158203125, "relay": "free_var %data: Tensor[(64, 18569), float32];\nnn.dense(%data, meta[relay.Constant][0], units=1953, out_dtype=\"float32\")\n"}