{"units": 4661, "features": 17600, "input shape": [null, 17600], "output shape": [null, 4661], "output dtype": "float32", "compute dtype": "float32", "workload": "dense", "layers": {"param": {"time": 0.0}, "tvmgen_default_fused_nn_dense": {"time": 20.445999999999998, "nvml:::NVIDIA_GeForce_GTX_980_Ti:device_1:power": 170475, "nvml:::NVIDIA_GeForce_GTX_980_Ti:device_1:gpu_utilization": 100, "nvml:::NVIDIA_GeForce_GTX_980_Ti:device_1:memory_utilization": 100, "nvml:::NVIDIA_GeForce_GTX_980_Ti:device_1:graphics_clock": 1265, "nvml:::NVIDIA_GeForce_GTX_980_Ti:device_1:sm_clock": 1265, "nvml:::NVIDIA_GeForce_GTX_980_Ti:device_1:memory_clock": 3304, "nvml:::NVIDIA_GeForce_GTX_980_Ti:device_1:allocated_memory": 434044928}}, "batch_size": 16, "time": 20.445999999999998, "power": 170.2425, "memory": 0.40423583984375, "relay": "free_var %data: Tensor[(16, 17600), float32];\nnn.dense(%data, meta[relay.Constant][0], units=4661, out_dtype=\"float32\")\n"}