{"units": 3768, "features": 18384, "input shape": [null, 18384], "output shape": [null, 3768], "output dtype": "float32", "compute dtype": "float32", "workload": "dense", "layers": {"param": {"time": 0.0}, "tvmgen_default_fused_nn_dense": {"time": 34.4542, "nvml:::NVIDIA_GeForce_GTX_980_Ti:device_1:power": 178630, "nvml:::NVIDIA_GeForce_GTX_980_Ti:device_1:gpu_utilization": 100, "nvml:::NVIDIA_GeForce_GTX_980_Ti:device_1:memory_utilization": 100, "nvml:::NVIDIA_GeForce_GTX_980_Ti:device_1:graphics_clock": 1265, "nvml:::NVIDIA_GeForce_GTX_980_Ti:device_1:sm_clock": 1265, "nvml:::NVIDIA_GeForce_GTX_980_Ti:device_1:memory_clock": 3304, "nvml:::NVIDIA_GeForce_GTX_980_Ti:device_1:allocated_memory": 384106496}}, "batch_size": 32, "time": 34.4542, "power": 178.422, "memory": 0.35772705078125, "relay": "free_var %data: Tensor[(32, 18384), float32];\nnn.dense(%data, meta[relay.Constant][0], units=3768, out_dtype=\"float32\")\n"}