{"units": 4135, "features": 16505, "input shape": [null, 16505], "output shape": [null, 4135], "output dtype": "float32", "compute dtype": "float32", "workload": "dense", "layers": {"param": {"time": 0.0}, "tvmgen_default_fused_nn_dense": {"time": 1.09043, "nvml:::NVIDIA_GeForce_GTX_980_Ti:device_1:power": 174371, "nvml:::NVIDIA_GeForce_GTX_980_Ti:device_1:gpu_utilization": 100, "nvml:::NVIDIA_GeForce_GTX_980_Ti:device_1:memory_utilization": 100, "nvml:::NVIDIA_GeForce_GTX_980_Ti:device_1:graphics_clock": 1265, "nvml:::NVIDIA_GeForce_GTX_980_Ti:device_1:sm_clock": 1265, "nvml:::NVIDIA_GeForce_GTX_980_Ti:device_1:memory_clock": 3304, "nvml:::NVIDIA_GeForce_GTX_980_Ti:device_1:allocated_memory": 377683968}}, "batch_size": 1, "time": 1.09043, "power": 174.195, "memory": 0.35174560546875, "relay": "free_var %data: Tensor[(1, 16505), float32];\nnn.dense(%data, meta[relay.Constant][0], units=4135, out_dtype=\"float32\")\n"}