{"units": 3036, "features": 10022, "input shape": [null, 10022], "output shape": [null, 3036], "output dtype": "float32", "compute dtype": "float32", "workload": "dense", "layers": {"param": {"time": 0.0}, "tvmgen_default_fused_nn_dense": {"time": 61.793800000000005, "nvml:::NVIDIA_GeForce_GTX_980_Ti:device_1:power": 183967, "nvml:::NVIDIA_GeForce_GTX_980_Ti:device_1:gpu_utilization": 100, "nvml:::NVIDIA_GeForce_GTX_980_Ti:device_1:memory_utilization": 100, "nvml:::NVIDIA_GeForce_GTX_980_Ti:device_1:graphics_clock": 1265, "nvml:::NVIDIA_GeForce_GTX_980_Ti:device_1:sm_clock": 1265, "nvml:::NVIDIA_GeForce_GTX_980_Ti:device_1:memory_clock": 3304, "nvml:::NVIDIA_GeForce_GTX_980_Ti:device_1:allocated_memory": 232194048}}, "batch_size": 128, "time": 61.793800000000005, "power": 183.597, "memory": 0.21624755859375, "relay": "free_var %data: Tensor[(128, 10022), float32];\nnn.dense(%data, meta[relay.Constant][0], units=3036, out_dtype=\"float32\")\n"}