{"units": 2835, "features": 13899, "input shape": [null, 13899], "output shape": [null, 2835], "output dtype": "float32", "compute dtype": "float32", "workload": "dense", "layers": {"param": {"time": 0.0}, "tvmgen_default_fused_nn_dense": {"time": 79.80760000000001, "nvml:::NVIDIA_GeForce_GTX_980_Ti:device_1:power": 189802, "nvml:::NVIDIA_GeForce_GTX_980_Ti:device_1:gpu_utilization": 100, "nvml:::NVIDIA_GeForce_GTX_980_Ti:device_1:memory_utilization": 100, "nvml:::NVIDIA_GeForce_GTX_980_Ti:device_1:graphics_clock": 1265, "nvml:::NVIDIA_GeForce_GTX_980_Ti:device_1:sm_clock": 1265, "nvml:::NVIDIA_GeForce_GTX_980_Ti:device_1:memory_clock": 3304, "nvml:::NVIDIA_GeForce_GTX_980_Ti:device_1:allocated_memory": 270073856}}, "batch_size": 128, "time": 79.80760000000001, "power": 189.496, "memory": 0.25152587890625, "relay": "free_var %data: Tensor[(128, 13899), float32];\nnn.dense(%data, meta[relay.Constant][0], units=2835, out_dtype=\"float32\")\n"}