{"pool_size": [2, 2], "stride": [4, 4], "padding": "valid", "input shape": [null, 113, 188, 800], "output shape": [null, 47, 28, 800], "output dtype": "float32", "compute dtype": "float32", "workload": "max_pool2d", "strides": [4, 4], "layers": {"param": {"time": 0.0}, "tvmgen_default_fused_nn_max_pool2d": {"time": 3.51551, "nvml:::Tesla_K80:device_0:power": 124643, "nvml:::Tesla_K80:device_0:gpu_utilization": 100, "nvml:::Tesla_K80:device_0:memory_utilization": 100, "nvml:::Tesla_K80:device_0:graphics_clock": 875, "nvml:::Tesla_K80:device_0:sm_clock": 875, "nvml:::Tesla_K80:device_0:memory_clock": 2505, "nvml:::Tesla_K80:device_0:allocated_memory": 1225785344}}, "data layout": "NCHW", "batch_size": 16, "time": 3.51551, "power": 118.609, "memory": 1.1416015625, "relay": "free_var %data: Tensor[(16, 800, 188, 113), float32];\nnn.max_pool2d(%data, pool_size=[2, 2], strides=[4, 4], padding=[0, 0, 0, 0], out_layout=\"NCHW\")"}