{"pool_size": [2, 2], "stride": [6, 6], "padding": "valid", "input shape": [null, 167, 39, 3702], "output shape": [null, 7, 28, 3702], "output dtype": "float32", "compute dtype": "float32", "workload": "max_pool2d", "strides": [6, 6], "layers": {"param": {"time": 0.0}, "tvmgen_default_fused_nn_max_pool2d": {"time": 14.6125, "nvml:::Tesla_K80:device_0:power": 117615, "nvml:::Tesla_K80:device_0:gpu_utilization": 100, "nvml:::Tesla_K80:device_0:memory_utilization": 100, "nvml:::Tesla_K80:device_0:graphics_clock": 875, "nvml:::Tesla_K80:device_0:sm_clock": 875, "nvml:::Tesla_K80:device_0:memory_clock": 2505, "nvml:::Tesla_K80:device_0:allocated_memory": 6431047680}}, "data layout": "NCHW", "batch_size": 64, "time": 14.6125, "power": 113.476, "memory": 5.9893798828125, "relay": "free_var %data: Tensor[(64, 3702, 39, 167), float32];\nnn.max_pool2d(%data, pool_size=[2, 2], strides=[6, 6], padding=[0, 0, 0, 0], out_layout=\"NCHW\")"}