{"filters": 128, "kernel": [1, 1], "strides": [1, 1], "padding": "valid", "dilation": [1, 1], "groups": 1, "input shape": [null, 7, 7, 1568], "output shape": [null, 7, 7, 128], "output dtype": "float32", "compute dtype": "float32", "workload": "conv2d", "layers": {"param": {"time": 0.0}, "tvmgen_default_fused_layout_transform": {"time": 42083.235, "energy": 1790035, "powercap:::ENERGY_UJ:ZONE0": 1790035, "powercap:::ENERGY_UJ:ZONE0_SUBZONE0": 0, "powercap:::ENERGY_UJ:ZONE0_SUBZONE1": 0, "power": 42.535584538593575}, "tvmgen_default_fused_nn_contrib_conv2d_NCHWc": {"time": 227458.097, "energy": 13153897, "powercap:::ENERGY_UJ:ZONE0": 13153897, "powercap:::ENERGY_UJ:ZONE0_SUBZONE0": 0, "powercap:::ENERGY_UJ:ZONE0_SUBZONE1": 0, "power": 57.82997911918695}, "tvmgen_default_fused_layout_transform_1": {"time": 1201.161, "energy": 50537, "powercap:::ENERGY_UJ:ZONE0": 50537, "powercap:::ENERGY_UJ:ZONE0_SUBZONE0": 0, "powercap:::ENERGY_UJ:ZONE0_SUBZONE1": 0, "power": 42.073460593542414}}, "data layout": "NCHW", "kernel layout": "OIHW", "batch_size": 32, "time": 5.44242, "power": 57.87483048073604, "memory": -1, "relay": "free_var %data: Tensor[(32, 1568, 7, 7), float32];\nnn.conv2d(%data, meta[relay.Constant][0], padding=[0, 0, 0, 0], channels=128, kernel_size=[1, 1])\n"}