{"filters": 240, "kernel": [1, 1], "strides": [1, 1], "padding": "same", "dilation": [1, 1], "groups": 1, "input shape": [null, 30, 30, 40], "output shape": [null, 30, 30, 240], "output dtype": "float32", "compute dtype": "float32", "workload": "conv2d", "layers": {"param": {"time": 0.0}, "tvmgen_default_fused_layout_transform": {"time": 25751.934, "energy": 1116574, "powercap:::ENERGY_UJ:ZONE0": 1116574, "powercap:::ENERGY_UJ:ZONE0_SUBZONE0": 0, "powercap:::ENERGY_UJ:ZONE0_SUBZONE1": 0, "power": 43.35884054378207}, "tvmgen_default_fused_nn_contrib_conv2d_NCHWc": {"time": 255224.883, "energy": 15256553, "powercap:::ENERGY_UJ:ZONE0": 15256553, "powercap:::ENERGY_UJ:ZONE0_SUBZONE0": 0, "powercap:::ENERGY_UJ:ZONE0_SUBZONE1": 0, "power": 59.77690270897293}, "tvmgen_default_fused_layout_transform_1": {"time": 186117.866, "energy": 8943458, "powercap:::ENERGY_UJ:ZONE0": 8943458, "powercap:::ENERGY_UJ:ZONE0_SUBZONE0": 0, "powercap:::ENERGY_UJ:ZONE0_SUBZONE1": 0, "power": 48.052657126425466}}, "data layout": "NCHW", "kernel layout": "OIHW", "batch_size": 64, "time": 9.0809, "power": 59.76935619870393, "memory": -1, "relay": "free_var %data: Tensor[(64, 40, 30, 30), float32];\nnn.conv2d(%data, meta[relay.Constant][0], padding=[0, 0, 0, 0], channels=240, kernel_size=[1, 1])\n"}