{"filters": 192, "kernel": [7, 1], "strides": [1, 1], "padding": "same", "dilation": [1, 1], "groups": 1, "input shape": [null, 17, 17, 192], "output shape": [null, 11, 17, 192], "output dtype": "float32", "compute dtype": "float32", "workload": "conv2d", "layers": {"param": {"time": 0.0}, "tvmgen_default_fused_layout_transform": {"time": 5651.904, "energy": 274291, "powercap:::ENERGY_UJ:ZONE0": 274291, "powercap:::ENERGY_UJ:ZONE0_SUBZONE0": 0, "powercap:::ENERGY_UJ:ZONE0_SUBZONE1": 0, "power": 48.53072522109363}, "tvmgen_default_fused_nn_contrib_conv2d_NCHWc": {"time": 269727.55, "energy": 16526813, "powercap:::ENERGY_UJ:ZONE0": 16526813, "powercap:::ENERGY_UJ:ZONE0_SUBZONE0": 0, "powercap:::ENERGY_UJ:ZONE0_SUBZONE1": 0, "power": 61.27224675417843}, "tvmgen_default_fused_layout_transform_1": {"time": 2916.531, "energy": 163086, "powercap:::ENERGY_UJ:ZONE0": 163086, "powercap:::ENERGY_UJ:ZONE0_SUBZONE0": 0, "powercap:::ENERGY_UJ:ZONE0_SUBZONE1": 0, "power": 55.91780097657114}}, "data layout": "NCHW", "kernel layout": "OIHW", "batch_size": 32, "time": 20.7826, "power": 61.16092021161753, "memory": -1, "relay": "free_var %data: Tensor[(32, 192, 17, 17), float32];\nnn.conv2d(%data, meta[relay.Constant][0], padding=[0, 0, 0, 0], channels=192, kernel_size=[7, 1])\n"}