{"filters": 64, "kernel": [7, 7], "strides": [2, 2], "padding": "valid", "dilation": [1, 1], "groups": 1, "input shape": [null, 230, 230, 3], "output shape": [null, 112, 112, 64], "output dtype": "float32", "compute dtype": "float32", "workload": "conv2d", "layers": {"param": {"time": 0.0}, "tvmgen_default_fused_layout_transform": {"time": 9463.471, "energy": 445006, "powercap:::ENERGY_UJ:ZONE0": 445006, "powercap:::ENERGY_UJ:ZONE0_SUBZONE0": 0, "powercap:::ENERGY_UJ:ZONE0_SUBZONE1": 0, "power": 47.02354981591849}, "tvmgen_default_fused_nn_contrib_conv2d_NCHWc": {"time": 210438.712, "energy": 12842862, "powercap:::ENERGY_UJ:ZONE0": 12842862, "powercap:::ENERGY_UJ:ZONE0_SUBZONE0": 0, "powercap:::ENERGY_UJ:ZONE0_SUBZONE1": 0, "power": 61.028989761161434}, "tvmgen_default_fused_layout_transform_1": {"time": 48066.669, "energy": 2507379, "powercap:::ENERGY_UJ:ZONE0": 2507379, "powercap:::ENERGY_UJ:ZONE0_SUBZONE0": 0, "powercap:::ENERGY_UJ:ZONE0_SUBZONE1": 0, "power": 52.164609118222856}}, "data layout": "NCHW", "kernel layout": "OIHW", "batch_size": 32, "time": 74.27499999999999, "power": 61.25654719040236, "memory": -1, "relay": "free_var %data: Tensor[(32, 3, 230, 230), float32];\nnn.conv2d(%data, meta[relay.Constant][0], strides=[2, 2], padding=[0, 0, 0, 0], channels=64, kernel_size=[7, 7])\n"}